Memory/Register Bank/RAM.v
module RAM(rw, chip_enable, enable, select1, select2, dataIn, source1, source2);

  input rw, chip_enable;
  input[2:0] enable, select1, select2;
  input [15:0] dataIn;
  
  reg [15:0] mem[0:7]; // memory array
  output reg [15:0] source1, source2;
  
  
  always @(*)
  begin
	if (chip_enable)
		if (rw)
		begin
			source1 = mem[select1];
			source2 = mem[select2];
		end
		else
			mem[enable] = dataIn;
	else
	begin
		source1 = 16'hzzzz;
		source2 = 16'hzzzz;
	end
   end
		
endmodule

Memory/splitter/splitter.v
/* ENGR 468 - Milestone #2 Memory
Decoder splitting module
*/

module splitter(inst, cond, opcd, dest, source, source2);

	input[15:0] inst; // 16 bit instruction input from ROM for decoding
	output [1:0] cond; // 2 bits MSG for condition
	output [3:0] opcd, source2; // op code and shift bits
	output [2:0] dest, source;  // 3bits desitination register (R7 max)
	
	assign cond = inst[15:14];
    assign opcd = inst[13:10];
	assign dest = inst[9:7];
	assign source = inst[6:4];
    assign source2 = inst[3:0];
	
endmodule

Memory/ROM/ROM.v
/* ENGR 468 - Milestone #2 Memory
ROM module
*/

module ROM(oeb, inst, pc);
  parameter Awidth = 4, Dwidth = 16;
  
  input oeb;
  reg rw;
  input[2:0] pc;
  //wire [Dwidth-1:0] next_inst; //read only output instruction set
  output reg[Dwidth-1:0] inst; //read only output instruction set

  localparam Length = (1 << Awidth);
  reg [Dwidth-1:0] mem[0:Length-1]; // initialize 8x16 memory address 
  
  
  always@(posedge oeb)
  begin
  
	rw = oeb;
	
	if (rw == 1)
		inst = mem[pc];	//pass instruction set through only on 'fetch' cycle
  end
  
  
endmodule

Memory/instruction_decoding_main.v
`include "\ROM\ROM.v"
`include "\splitter\splitter.v"
`include "\Register Bank\RAM.v"



module instr_mem_decoder_main(source1, source2, opcode, clock);

	input clock;
	input [15:0] ALU_data;		       // output from ALU to be written back to reg bank
	
	reg rw;
	reg[1:0] current_state, next_state;
	reg[2:0] pc; 					// program counter  
	reg rw_RAM, chip_enable;
	
	output[15:0] source1, source2;// decoded register data to ALU
	
	wire[15:0] inst;            // fetched instruction set from ROM
	wire[2:0] en; 	           // enable signals to register set			  
	output[3:0] opcode; 
	wire[2:0] dest, select1;
	wire[3:0]select2;
	
	
	// FSM state (fetch, decode, execute) architecture
	always@(current_state)
	begin
		
		chip_enable = 1;
	
		if (current_state == 2)	//during execution, write back ALU data to RAM and increment PC
		begin
			rw = 0;
			next_state = 0;
			pc = pc +1;
			rw_RAM = 0;
		end
		
		else if(current_state ==1)	// during execution, turn ROM to high-impedance, read desired registers and output to ALU
		begin
			rw = 0;	
			rw_RAM = 1; 
			next_state = current_state + 1;
		end
		else	
		begin
			rw= 1;
			rw_RAM = 0;
			next_state = current_state +1;
		end	
	end
	
	
	always@(posedge clock)
	begin
		current_state = next_state;
	end
	
	
	// connect sub-modules to generate hardware architecture
	ROM rom(.oeb(rw),
			.inst(inst),
			.pc(pc)
			);
			
			
	splitter split(.inst(inst),
        	       .cond(),
  				   .opcd(opcode),
				   .dest(dest),
				   .source(select1),
				   .source2(select2)
				   );
	
	RAM ram(.rw(rw_RAM),
			.chip_enable(chip_enable),
			.enable(en),
			.select1(select1),
			.select2(select2[3:1]),
			.dataIn(ALU_data),
			.source1(source1),
			.source2(source2));
		 
endmodule

Memory/instruction_decoding_main_tb.v
`include "instruction_decoding_main.v"

module instr_mem_decoder_main_tb();

	reg oeb, clock; 				  
	reg[15:0] ALU_data;		       
		
	wire[15:0] source1, source2;   
	
	wire[3:0] opcode;
	
	integer i;
	
	instr_mem_decoder_main MUT(source1, source2, opcode, clock);
	
	
	initial
	begin
	
		$dumpfile("module2_test.vcd");
		$dumpvars(0,instr_mem_decoder_main_tb);
		
		MUT.current_state = 0;
		MUT.pc = 0;
		MUT.rw_RAM = 1;
		MUT.chip_enable = 1;
		MUT.rw = 1;
		
		
		$readmemb("ROM_instructions.txt", MUT.rom.mem); // intialize ROM memory

		
		for(i=0; i<16; i = i+1)
		begin	
			$display("data[%d] = %h", i, MUT.rom.mem[i]);
		end
		
		$writememh("ROM_filled.txt", MUT.rom.mem);
		$readmemh("initial_ram_data.txt", MUT.ram.mem); // initialize RAM memory 

		
		oeb = 1;
		clock = 0;
		ALU_data = 16'h0001;
		
		#300;
		
		ALU_data = 16'hFFFF;
		
		$finish();	
	end
	
	initial 
	begin
		$monitor("clock =%d, current_state =%d, pc = %d, inst=%h, rw_RAM =%b, dataIn =%h, source1=%h, source2=%h, select1= %d, select2 = %d", clock, MUT.current_state, MUT.pc, MUT.inst, MUT.rw_RAM, ALU_data, source1, source2, MUT.select1, MUT.select2);
	end
	
	
	always
	begin	
		clock = !clock;
		#5;
	end
endmodule

Memory/module2_test.vcd
$date
	Sat Nov 18 17:12:13 2017
$end
$version
	Icarus Verilog
$end
$timescale
	1s
$end
$scope module instr_mem_decoder_main_tb $end
$var wire 16 ! source2 [15:0] $end
$var wire 16 " source1 [15:0] $end
$var wire 4 # opcode [3:0] $end
$var reg 16 $ ALU_data [15:0] $end
$var reg 1 % clock $end
$var reg 1 & oeb $end
$var integer 32 ' i [31:0] $end
$scope module MUT $end
$var wire 16 ( ALU_data [15:0] $end
$var wire 1 % clock $end
$var wire 3 ) en [2:0] $end
$var wire 16 * source2 [15:0] $end
$var wire 16 + source1 [15:0] $end
$var wire 4 , select2 [3:0] $end
$var wire 3 - select1 [2:0] $end
$var wire 4 . opcode [3:0] $end
$var wire 16 / inst [15:0] $end
$var wire 3 0 dest [2:0] $end
$var reg 1 1 chip_enable $end
$var reg 2 2 current_state [1:0] $end
$var reg 2 3 next_state [1:0] $end
$var reg 3 4 pc [2:0] $end
$var reg 1 5 rw $end
$var reg 1 6 rw_RAM $end
$scope module ram $end
$var wire 1 1 chip_enable $end
$var wire 16 7 dataIn [15:0] $end
$var wire 3 8 enable [2:0] $end
$var wire 1 6 rw $end
$var wire 3 9 select2 [2:0] $end
$var wire 3 : select1 [2:0] $end
$var reg 16 ; source1 [15:0] $end
$var reg 16 < source2 [15:0] $end
$upscope $end
$scope module rom $end
$var wire 1 5 oeb $end
$var wire 3 = pc [2:0] $end
$var reg 16 > inst [15:0] $end
$var reg 1 ? rw $end
$upscope $end
$scope module split $end
$var wire 16 @ inst [15:0] $end
$var wire 4 A source2 [3:0] $end
$var wire 3 B source [2:0] $end
$var wire 4 C opcd [3:0] $end
$var wire 3 D dest [2:0] $end
$var wire 2 E cond [1:0] $end
$upscope $end
$upscope $end
$upscope $end
$enddefinitions $end
#0
$dumpvars
b0 E
b1 D
b1 C
b10 B
b0 A
b10010100000 @
1?
b10010100000 >
b0 =
b1111111111111111 <
b10 ;
b10 :
b0 9
bz 8
bz 7
16
05
b0 4
b10 3
b1 2
11
b1 0
b10010100000 /
b1 .
b10 -
b0 ,
b10 +
b1111111111111111 *
bz )
bz (
b10000 '
1&
1%
b1 $
b1 #
b10 "
b1111111111111111 !
$end
#5
0%
#10
06
b1 4
b1 =
b0 3
b10 2
1%
#15
0%
#20
b10 #
b10 .
b10 C
b1 -
b1 :
b1 B
b100010010000 /
b100010010000 >
b100010010000 @
b1 3
15
b0 2
1%
#25
0%
#30
b1 "
b1 +
b1 ;
b10 3
16
05
b1 2
1%
#35
0%
#40
06
b10 4
b10 =
b0 3
b10 2
1%
#45
0%
#50
b11 #
b11 .
b11 C
b10 -
b10 :
b10 B
b110010100000 /
b110010100000 >
b110010100000 @
b1 3
15
b0 2
1%
#55
0%
#60
b10 "
b10 +
b10 ;
b10 3
16
05
b1 2
1%
#65
0%
#70
06
b11 4
b11 =
b0 3
b10 2
1%
#75
0%
#80
b100 #
b100 .
b100 C
b1000010100000 /
b1000010100000 >
b1000010100000 @
b1 3
15
b0 2
1%
#85
0%
#90
b10 3
16
05
b1 2
1%
#95
0%
#100
06
b100 4
b100 =
b0 3
b10 2
1%
#105
0%
#110
b101 #
b101 .
b101 C
b11 -
b11 :
b11 B
b1 ,
b1 A
b1010010110001 /
b1010010110001 >
b1010010110001 @
b1 3
15
b0 2
1%
#115
0%
#120
b11 "
b11 +
b11 ;
b10 3
16
05
b1 2
1%
#125
0%
#130
06
b101 4
b101 =
b0 3
b10 2
1%
#135
0%
#140
b110 #
b110 .
b110 C
b10 -
b10 :
b10 B
b0 ,
b0 A
b1100010100000 /
b1100010100000 >
b1100010100000 @
b1 3
15
b0 2
1%
#145
0%
#150
b10 "
b10 +
b10 ;
b10 3
16
05
b1 2
1%
#155
0%
#160
06
b110 4
b110 =
b0 3
b10 2
1%
#165
0%
#170
b111 #
b111 .
b111 C
b111 -
b111 :
b111 B
b1 ,
b1 A
b1110011110001 /
b1110011110001 >
b1110011110001 @
b1 3
15
b0 2
1%
#175
0%
#180
b1111111111111111 "
b1111111111111111 +
b1111111111111111 ;
b10 3
16
05
b1 2
1%
#185
0%
#190
06
b111 4
b111 =
b0 3
b10 2
1%
#195
0%
#200
b1 9
b1000 #
b1000 .
b1000 C
b10 -
b10 :
b10 B
b11 ,
b11 A
b10000010100011 /
b10000010100011 >
b10000010100011 @
b1 3
15
b0 2
1%
#205
0%
#210
b1 !
b1 *
b1 <
b10 "
b10 +
b10 ;
b10 3
16
05
b1 2
1%
#215
0%
#220
06
b0 4
b0 =
b0 3
b10 2
1%
#225
0%
#230
b0 9
b1 #
b1 .
b1 C
b0 ,
b0 A
b10010100000 /
b10010100000 >
b10010100000 @
b1 3
15
b0 2
1%
#235
0%
#240
b1111111111111111 !
b1111111111111111 *
b1111111111111111 <
b10 3
16
05
b1 2
1%
#245
0%
#250
06
b1 4
b1 =
b0 3
b10 2
1%
#255
0%
#260
b10 #
b10 .
b10 C
b1 -
b1 :
b1 B
b100010010000 /
b100010010000 >
b100010010000 @
b1 3
15
b0 2
1%
#265
0%
#270
b1 "
b1 +
b1 ;
b10 3
16
05
b1 2
1%
#275
0%
#280
06
b10 4
b10 =
b0 3
b10 2
1%
#285
0%
#290
b11 #
b11 .
b11 C
b10 -
b10 :
b10 B
b110010100000 /
b110010100000 >
b110010100000 @
b1 3
15
b0 2
1%
#295
0%
#300
b10 "
b10 +
b10 ;
b10 3
16
05
b1 2
1%
b1111111111111111 $
